pybrotlib/__init__.py
pybrotlib/brot.py
pybrotlib/components/__init__.py
pybrotlib/components/base.py
pybrotlib/components/dome.py
pybrotlib/components/focus.py
pybrotlib/components/mirrorcovers.py
pybrotlib/components/roof.py
pybrotlib/components/telescope.py
pybrotlib/py.typed
pybrotlib/telemetry.py
pybrotlib/transport/__init__.py
pybrotlib/transport/mqtttransport.py
pybrotlib/transport/transport.py
pybrotlib-0.3.0.dist-info/WHEEL
pybrotlib-0.3.0.dist-info/METADATA
pybrotlib-0.3.0.dist-info/RECORD
