Metadata-Version: 2.4
Name: pyBROTlib
Version: 0.3.0
Summary: MQTT interface to BROT telescopes
Author: Tim-Oliver Husser, Lukas Melzig
Author-email: Tim-Oliver Husser <thusser@uni-goettingen.de>, Lukas Melzig <lukas.melzig@stud.uni-goettingen.de>
License-Expression: MIT
Requires-Dist: aiomqtt>=2.4.0
Requires-Python: >=3.11
